caliph/__init__.py
caliph/cli.py
caliph/routines.py
caliph-0.2.1.dist-info/entry_points.txt
caliph-0.2.1.dist-info/LICENSE
caliph-0.2.1.dist-info/WHEEL
caliph-0.2.1.dist-info/METADATA
caliph-0.2.1.dist-info/RECORD
